jira_cloud_api/__init__.py
jira_cloud_api/jira_api.py
jira_cloud_api/jira_models.py
jira_cloud_api/jira_request.py
jira_cloud_api/jira_response.py
jira_cloud_api/py.typed
jira_cloud_api-0.1.0.dist-info/LICENSE
jira_cloud_api-0.1.0.dist-info/METADATA
jira_cloud_api-0.1.0.dist-info/WHEEL
jira_cloud_api-0.1.0.dist-info/RECORD
