Metadata-Version: 2.3
Name: jira-cloud-api
Version: 0.1.0
Summary: An elegant way to interact with Jira.
License: MIT
Author: Sharry
Author-email: sharry.xu@outlook.com
Requires-Python: >=3.10
Classifier: License :: OSI Approved :: MIT License
Classifier: Programming Language :: Python :: 3
Classifier: Programming Language :: Python :: 3.10
Classifier: Programming Language :: Python :: 3.11
Classifier: Programming Language :: Python :: 3.12
Classifier: Programming Language :: Python :: 3.13
Requires-Dist: dateparser (>=1.2.2,<2.0.0)
Requires-Dist: requests (>=2.32.4)
Requires-Dist: typing-extensions (>=4.14.1,<5.0.0)
Requires-Dist: urllib3 (>=2.5.0,<3.0.0)
